illustris_python/__init__.py
illustris_python/cartesian.py
illustris_python/groupcat.py
illustris_python/lhalotree.py
illustris_python/snapshot.py
illustris_python/sublink.py
illustris_python/util.py
illustris_python-1.1.1.dist-info/licenses/LICENSE.md
illustris_python-1.1.1.dist-info/METADATA
illustris_python-1.1.1.dist-info/WHEEL
illustris_python-1.1.1.dist-info/top_level.txt
illustris_python-1.1.1.dist-info/RECORD
